README.txt
setup.py
tests/__init__.py
tests/conftest.py
tests/test_provider.py
tests/test_request.py
wsgioauth/__init__.py
wsgioauth/calls.py
wsgioauth/consumer.py
wsgioauth/mock.py
wsgioauth/provider.py
wsgioauth/request.py
wsgioauth/run.py
wsgioauth/signatures.py
wsgioauth/utils.py
wsgioauth/xmlrpc.py
wsgioauth.egg-info/PKG-INFO
wsgioauth.egg-info/SOURCES.txt
wsgioauth.egg-info/dependency_links.txt
wsgioauth.egg-info/entry_points.txt
wsgioauth.egg-info/namespace_packages.txt
wsgioauth.egg-info/not-zip-safe
wsgioauth.egg-info/requires.txt
wsgioauth.egg-info/top_level.txt