Metadata-Version: 1.0
Name: wsgioauth
Version: 0.1
Summary: A WSGI OAuth packageapplication and middlware.
Home-page: http://weblion.psu.edu/
Author: Michael Mulich | WebLion Group, Penn State University
Author-email: support@weblion.psu.edu
License: GPL
Keywords: web wsgi oauth authentication authorization
Platform: UNKNOWN
Classifier: Development Status :: 2 - Pre-Alpha
Classifier: Programming Language :: Python
Classifier: Topic :: Security
Classifier: Topic :: Internet :: WWW/HTTP
Classifier: Topic :: Internet :: WWW/HTTP :: WSGI
Classifier: Topic :: Internet :: WWW/HTTP :: WSGI :: Application
Classifier: Topic :: Internet :: WWW/HTTP :: WSGI :: Middleware
